simple_components/__init__.py
simple_components/apps.py
simple_components/exceptions.py
simple_components/templates/simple_components/base.html
simple_components/templates/simple_components/slots.html
simple_components/templatetags/__init__.py
simple_components/templatetags/simple_components.py
django_simple_components-0.1.0.dist-info/LICENSE
django_simple_components-0.1.0.dist-info/METADATA
django_simple_components-0.1.0.dist-info/WHEEL
django_simple_components-0.1.0.dist-info/top_level.txt
django_simple_components-0.1.0.dist-info/RECORD
