Metadata-Version: 2.1
Name: django-simple-components
Version: 0.1.0
Summary: A small package to easily create components inside your templates without saving them in the templates folder.
Author-email: Pavel Kutsenko <zebartcoc@gmail.com>
Project-URL: Homepage, https://github.com/paqstd-dev/django-simple-components
Project-URL: Bug Tracker, https://github.com/paqstd-dev/django-simple-components/issues
Classifier: Environment :: Web Environment
Classifier: Framework :: Django
Classifier: Framework :: Django :: 3.2
Classifier: Framework :: Django :: 4.1
Classifier: Framework :: Django :: 4.2
Classifier: Intended Audience :: Developers
Classifier: License :: OSI Approved :: MIT License
Classifier: Programming Language :: Python
Classifier: Programming Language :: Python :: 3
Classifier: Programming Language :: Python :: 3 :: Only
Classifier: Programming Language :: Python :: 3.8
Classifier: Programming Language :: Python :: 3.9
Classifier: Programming Language :: Python :: 3.10
Classifier: Programming Language :: Python :: 3.11
Requires-Python: >=3.8
License-File: LICENSE
